README.rst
setup.py
src/benchsuite/__init__.py
src/benchsuite.core.egg-info/PKG-INFO
src/benchsuite.core.egg-info/SOURCES.txt
src/benchsuite.core.egg-info/dependency_links.txt
src/benchsuite.core.egg-info/namespace_packages.txt
src/benchsuite.core.egg-info/requires.txt
src/benchsuite.core.egg-info/top_level.txt
src/benchsuite/core/__init__.py
src/benchsuite/core/config.py
src/benchsuite/core/controller.py
src/benchsuite/core/sessionmanager.py
src/benchsuite/core/model/__init__.py
src/benchsuite/core/model/benchmark.py
src/benchsuite/core/model/common.py
src/benchsuite/core/model/exception.py
src/benchsuite/core/model/execution.py
src/benchsuite/core/model/provider.py
src/benchsuite/core/model/session.py
src/benchsuite/core/model/storage.py